tcpliveplot
