Metadata-Version: 1.1
Name: tcpliveplot
Version: 0.2.7
Summary: Realtime-visualization of TCP flows logged by TCPlog.
Home-page: https://git.scc.kit.edu/CPUnetLOG/TCPlivePLOT/
Author: Michael Koenig
Author-email: michael.koenig2@student.kit.edu
License: BSD
Keywords: tcp,flow,plot,visualize,graph,live,analyze,network,traffic
Platform: Linux
Classifier: Development Status :: 4 - Beta
Classifier: License :: OSI Approved :: BSD License
Classifier: Programming Language :: Python :: 3
Classifier: Programming Language :: Python :: 3.5
Classifier: Operating System :: POSIX :: Linux
Classifier: Natural Language :: English
Classifier: Intended Audience :: Education
Classifier: Intended Audience :: Information Technology
Classifier: Intended Audience :: Science/Research
Classifier: Intended Audience :: System Administrators
Classifier: Intended Audience :: Telecommunications Industry
Classifier: Topic :: Scientific/Engineering
Classifier: Topic :: Internet
Classifier: Topic :: System :: Logging
Classifier: Topic :: System :: Networking
Classifier: Topic :: System :: Networking :: Monitoring
Classifier: Topic :: System :: Operating System Kernels :: Linux
Classifier: Topic :: Utilities
